CLA ADDER/VERILOG/verilog_vlsi_project.v
module dflipflop(
    output reg q,
    input d,
    input clk
);
    always @(posedge clk) begin
        q<=d;
    end
endmodule

module carry_lookahead_adder(
    input [3:0] A,   // 4-bit input A
    input [3:0] B,   // 4-bit input B
    input C0,        // Initial carry-in
    output [3:0] S,  // 4-bit sum
    output C4        // Final carry-out
);
    wire [3:0] P; // Propagate signals
    wire [3:0] G; // Generate signals
    wire C1, C2, C3; // Carry signals

    // Find P[i] (propagate) and G[i] (generate) for each bit
    xor u1(P[0], A[0], B[0]);
    xor u2(P[1], A[1], B[1]);
    xor u3(P[2], A[2], B[2]);
    xor u4(P[3], A[3], B[3]);

    and u5(G[0], A[0], B[0]);
    and u6(G[1], A[1], B[1]);
    and u7(G[2], A[2], B[2]);
    and u8(G[3], A[3], B[3]);

    // Find carry signals (C1, C2, C3, C4)
    wire a1, a2_1, a2_2, a3_1, a3_2, a3_3, a4_1, a4_2, a4_3, a4_4;

    // C1 = G[0] | (P[0] & C0)
    and u9(a1, P[0], C0);
    or u10(C1, G[0], a1);

    // C2 = G[1] | (P[1] & G[0]) | (P[1] & P[0] & C0)
    and u11(a2_1, P[1], P[0], C0);
    and u12(a2_2, P[1], G[0]);
    or u13(C2, G[1], a2_1, a2_2);

    // C3 = G[2] | (P[2] & G[1]) | (P[2] & P[1] & G[0]) | (P[2] & P[1] & P[0] & C0)
    and u14(a3_1, P[2], P[1], P[0], C0);
    and u15(a3_2, P[2], P[1], G[0]);
    and u16(a3_3, P[2], G[1]);
    or u17(C3, G[2], a3_1, a3_2, a3_3);

    // C4 = G[3] | (P[3] & G[2]) | (P[3] & P[2] & G[1]) | (P[3] & P[2] & P[1] & G[0]) | (P[3] & P[2] & P[1] & P[0] & C0)
    and u18(a4_1, P[3], P[2], P[1], P[0], C0);
    and u19(a4_2, P[3], P[2], P[1], G[0]);
    and u20(a4_3, P[3], P[2], G[1]);
    and u21(a4_4, P[3], G[2]);
    or u22(C4, G[3], a4_1, a4_2, a4_3, a4_4);

    // Find S[i] (Sum) for each bit
    xor u23(S[0], P[0], C0);
    xor u24(S[1], P[1], C1);
    xor u25(S[2], P[2], C2);
    xor u26(S[3], P[3], C3);
endmodule

module finalcircuit(    
    input [3:0] A,   // 4-bit input A
    input [3:0] B,   // 4-bit input B
    input C0,        // Initial carry-in
    input clk,
    output [3:0] S,  // 4-bit sum
    output C4        // Final carry-out);
);
    wire [3:0] A_ff,B_ff,S_ff;
    wire C4_ff;
    dflipflop dff1(A_ff[0],A[0],clk);
    dflipflop dff2(A_ff[1],A[1],clk);
    dflipflop dff3(A_ff[2],A[2],clk);
    dflipflop dff4(A_ff[3],A[3],clk);

    dflipflop dff5(B_ff[0],B[0],clk);
    dflipflop dff6(B_ff[1],B[1],clk);
    dflipflop dff7(B_ff[2],B[2],clk);
    dflipflop dff8(B_ff[3],B[3],clk);

    carry_lookahead_adder cla(.A(A_ff), .B(B_ff), .C0(C0), .S(S_ff), .C4(C4_ff));

    dflipflop dff9(S[0],S_ff[0],clk);
    dflipflop dff10(S[1],S_ff[1],clk);
    dflipflop dff11(S[2],S_ff[2],clk);
    dflipflop dff12(S[3],S_ff[3],clk);

    dflipflop dff13(C4,C4_ff,clk);
endmodule

CLA ADDER/VERILOG/testbench.v
`include "verilog_vlsi_project.v"

module testbench;
    reg [3:0] A, B;  // Test inputs
    reg C0;          // Initial carry
    reg clk;         // Clock signal
    wire [3:0] S;    // Sum output
    wire C4;         // Final carry output

    // Instantiate the carry lookahead adder
    finalcircuit cla (
        .A(A),
        .B(B),
        .C0(C0),
        .clk(clk),
        .S(S),
        .C4(C4)
    );

    // Generate clock signal
    always #5 clk = ~clk;

    // Test input signals
    initial begin
        $dumpfile("testbench.vcd");
        $dumpvars(0, testbench);
        clk = 1'b0; // Initialize clock
        A = 4'b1001; // Initial values
        B = 4'b1101;
        C0 = 1'b0;
        
        $monitor("Time=%0t A=%b B=%b C0=%b S=%b C4=%b", $time, A, B, C0, S, C4);

        #20 A = 4'b1010; // Change inputs
        #20 B = 4'b0101;
        #20 $finish; // Stop the simulation
    end
endmodule

CLA ADDER/VERILOG/testbench.vcd
$date
	Wed Nov 20 16:36:10 2024
$end
$version
	Icarus Verilog
$end
$timescale
	1s
$end
$scope module testbench $end
$var wire 4 ! S [3:0] $end
$var wire 1 " C4 $end
$var reg 4 # A [3:0] $end
$var reg 4 $ B [3:0] $end
$var reg 1 % C0 $end
$var reg 1 & clk $end
$scope module cla $end
$var wire 4 ' A [3:0] $end
$var wire 4 ( B [3:0] $end
$var wire 1 % C0 $end
$var wire 1 & clk $end
$var wire 4 ) S_ff [3:0] $end
$var wire 4 * S [3:0] $end
$var wire 1 + C4_ff $end
$var wire 1 " C4 $end
$var wire 4 , B_ff [3:0] $end
$var wire 4 - A_ff [3:0] $end
$scope module cla $end
$var wire 4 . A [3:0] $end
$var wire 4 / B [3:0] $end
$var wire 1 % C0 $end
$var wire 1 0 C1 $end
$var wire 1 1 C2 $end
$var wire 1 2 C3 $end
$var wire 1 + C4 $end
$var wire 1 3 a1 $end
$var wire 1 4 a2_1 $end
$var wire 1 5 a2_2 $end
$var wire 1 6 a3_1 $end
$var wire 1 7 a3_2 $end
$var wire 1 8 a3_3 $end
$var wire 1 9 a4_1 $end
$var wire 1 : a4_2 $end
$var wire 1 ; a4_3 $end
$var wire 1 < a4_4 $end
$var wire 4 = S [3:0] $end
$var wire 4 > P [3:0] $end
$var wire 4 ? G [3:0] $end
$upscope $end
$scope module dff1 $end
$var wire 1 & clk $end
$var wire 1 @ d $end
$var reg 1 A q $end
$upscope $end
$scope module dff10 $end
$var wire 1 & clk $end
$var wire 1 B d $end
$var reg 1 C q $end
$upscope $end
$scope module dff11 $end
$var wire 1 & clk $end
$var wire 1 D d $end
$var reg 1 E q $end
$upscope $end
$scope module dff12 $end
$var wire 1 & clk $end
$var wire 1 F d $end
$var reg 1 G q $end
$upscope $end
$scope module dff13 $end
$var wire 1 & clk $end
$var wire 1 + d $end
$var reg 1 " q $end
$upscope $end
$scope module dff2 $end
$var wire 1 & clk $end
$var wire 1 H d $end
$var reg 1 I q $end
$upscope $end
$scope module dff3 $end
$var wire 1 & clk $end
$var wire 1 J d $end
$var reg 1 K q $end
$upscope $end
$scope module dff4 $end
$var wire 1 & clk $end
$var wire 1 L d $end
$var reg 1 M q $end
$upscope $end
$scope module dff5 $end
$var wire 1 & clk $end
$var wire 1 N d $end
$var reg 1 O q $end
$upscope $end
$scope module dff6 $end
$var wire 1 & clk $end
$var wire 1 P d $end
$var reg 1 Q q $end
$upscope $end
$scope module dff7 $end
$var wire 1 & clk $end
$var wire 1 R d $end
$var reg 1 S q $end
$upscope $end
$scope module dff8 $end
$var wire 1 & clk $end
$var wire 1 T d $end
$var reg 1 U q $end
$upscope $end
$scope module dff9 $end
$var wire 1 & clk $end
$var wire 1 V d $end
$var reg 1 W q $end
$upscope $end
$upscope $end
$upscope $end
$enddefinitions $end
$comment Show the parameter values. $end
$dumpall
$end
#0
$dumpvars
xW
xV
xU
1T
xS
1R
xQ
0P
xO
1N
xM
1L
xK
0J
xI
0H
xG
xF
xE
xD
xC
xB
xA
1@
bx ?
bx >
bx =
x<
x;
x:
09
x8
x7
06
x5
04
03
x2
x1
x0
bx /
bx .
bx -
bx ,
x+
bx *
bx )
b1101 (
b1001 '
0&
0%
b1101 $
b1001 #
x"
bx !
$end
#5
1D
0F
1B
0V
01
02
1+
b110 )
b110 =
10
05
07
08
0:
0;
0<
b100 >
b1001 ?
1A
0I
0K
b1001 -
b1001 .
1M
1O
0Q
1S
b1101 ,
b1101 /
1U
1&
#10
0&
#15
1"
0G
1E
1C
b110 !
b110 *
0W
1&
#20
0@
1H
0&
b1010 #
b1010 '
#25
1V
1B
00
b111 )
b111 =
b1000 ?
b111 >
0A
b1010 -
b1010 .
1I
1&
#30
0&
#35
b111 !
b111 *
1W
1&
#40
0T
0&
b101 $
b101 (
#45
1F
0+
b1111 )
b1111 =
b1111 >
b0 ?
b101 ,
b101 /
0U
1&
#50
0&
#55
0"
b1111 !
b1111 *
1G
1&
